yamlres/__init__.py
yamlres/functional.py
yamlres/loader.py
yamlres/runner.py
yamlres-0.1.3.dist-info/METADATA
yamlres-0.1.3.dist-info/WHEEL
yamlres-0.1.3.dist-info/top_level.txt
yamlres-0.1.3.dist-info/RECORD
