Metadata-Version: 2.1
Name: yamlres
Version: 0.1.3
Summary: A yaml-based declarative programming interface
Home-page: https://github.com/maniospas/yamlres
Author: Emmanouil (Manios) Krasanakis
Author-email: maniospas@hotmail.com
License: UNKNOWN
Platform: UNKNOWN
Classifier: Programming Language :: Python :: 3
Classifier: License :: OSI Approved :: Apache Software License
Classifier: Operating System :: OS Independent
Requires-Dist: pyyaml
Requires-Dist: wget
